{
  "synthetic_dummy": false,
  "task": "urban-traffic-forecasting",
  "phase": "Phase 2-B — STGNN 학습 + RQ1 절제",
  "note": "SOTA 재현 아님(원리 재현). 결측=0 masked MAE/RMSE/MAPE. 논문값은 reference_only.",
  "dataset": {
    "name": "PEMS-BAY",
    "id": "pems-bay",
    "shape_T_N": [
      52116,
      325
    ],
    "sample_freq_min": 5,
    "source": "liyaguang/DCRNN (연구용 공개)"
  },
  "protocol": {
    "seq_len_in": 12,
    "horizon": 12,
    "horizons_steps": [
      3,
      6,
      12
    ],
    "horizons_minutes": {
      "h3": 15,
      "h6": 30,
      "h12": 60
    },
    "split_windows": {
      "train": 36465,
      "val": 5209,
      "test": 10419
    },
    "eval_split": "test",
    "features": [
      "zscore_speed",
      "time_of_day"
    ],
    "loss": "masked_mae(원 단위)",
    "adj_edge_density": 0.0255
  },
  "run": {
    "seed": 42,
    "git_commit": "693178be7b93b5a1a026f0c43f168f21d0f599d5",
    "timestamp_utc": "20260704T082908Z",
    "epochs_cap": 50,
    "batch_size": 256,
    "lr": 0.001,
    "weight_decay": 0.0001,
    "early_stop_patience": 10,
    "hardware": {
      "platform": "Windows-11-10.0.26200-SP0",
      "device": "cuda",
      "gpu": "NVIDIA GeForce RTX 3060",
      "cuda_fallback_to_cpu": false
    }
  },
  "stgnn_test": {
    "fixed": {
      "at_horizons": {
        "horizons": [
          3,
          6,
          12
        ],
        "mae": {
          "h3": 1.4752915131833089,
          "h6": 1.9800020396013718,
          "h12": 2.64693043456048
        },
        "rmse": {
          "h3": 3.105629622084711,
          "h6": 4.431802029176531,
          "h12": 5.901516253676324
        },
        "mape": {
          "h3": 3.1131059964539802,
          "h6": 4.445373848968144,
          "h12": 6.435106382120343
        }
      },
      "per_step": {
        "per_step": {
          "mae": [
            0.9423619510711355,
            1.2431363096153412,
            1.4752915131833089,
            1.6669023747086813,
            1.832325060002267,
            1.9800020396013718,
            2.1141824267290774,
            2.2376304850095794,
            2.3492341026739996,
            2.4546956412114382,
            2.5509927597317494,
            2.64693043456048
          ],
          "rmse": [
            1.715189900480787,
            2.468897709832358,
            3.105629622084711,
            3.6296807984860577,
            4.065272882995028,
            4.431802029176531,
            4.748787535301377,
            5.025238520069341,
            5.269177847058111,
            5.4983375788851,
            5.701786011557693,
            5.901516253676324
          ],
          "mape": [
            1.9014103625135996,
            2.557935418143316,
            3.1131059964539802,
            3.6054487098639836,
            4.046283572775933,
            4.445373848968144,
            4.825022993010639,
            5.195274256329495,
            5.529158941991547,
            5.846163480426799,
            6.155026102470915,
            6.435106382120343
          ]
        },
        "mean": {
          "mae": 1.9578070915082024,
          "rmse": 4.296776390800285,
          "mape": 4.471275838755724
        }
      },
      "mae_divergence": {
        "slope": 0.14733757191469793,
        "final_over_first": 2.808825665713526,
        "monotonic_frac": 1.0
      },
      "train_meta": {
        "n_params": 15148,
        "best_val_mae": 2.184178272883097,
        "best_epoch": 45,
        "epochs_run": 50,
        "train_time_sec": 771.0,
        "peak_vram_gb": 2.22
      }
    },
    "learned": {
      "at_horizons": {
        "horizons": [
          3,
          6,
          12
        ],
        "mae": {
          "h3": 1.4326671151301802,
          "h6": 1.8663407693036878,
          "h12": 2.4003403331864854
        },
        "rmse": {
          "h3": 2.9621935063108413,
          "h6": 4.05539644293632,
          "h12": 5.251757415197859
        },
        "mape": {
          "h3": 3.0831501027166675,
          "h6": 4.3441569932751944,
          "h12": 5.985404661043615
        }
      },
      "per_step": {
        "per_step": {
          "mae": [
            0.9389895752755499,
            1.2219771256527767,
            1.4326671151301802,
            1.602356070733819,
            1.7434066532730548,
            1.8663407693036878,
            1.9754558629800898,
            2.0701350845583892,
            2.164972980160502,
            2.2456402818627637,
            2.322687888653568,
            2.4003403331864854
          ],
          "rmse": [
            1.6888902665432457,
            2.3964718810744534,
            2.9621935063108413,
            3.4094200927073333,
            3.766401654369935,
            4.05539644293632,
            4.305992853874549,
            4.525160595631237,
            4.7355045790818835,
            4.924402308681776,
            5.089643500264317,
            5.251757415197859
          ],
          "mape": [
            1.9016691077820174,
            2.5402080206549904,
            3.0831501027166675,
            3.5504874761749163,
            3.9734450838763107,
            4.3441569932751944,
            4.669422583478113,
            4.96137350750399,
            5.27237377192212,
            5.533179474101493,
            5.7504399232482015,
            5.985404661043615
          ]
        },
        "mean": {
          "mae": 1.8320808117309053,
          "rmse": 3.9259362580561454,
          "mape": 4.29710922548147
        }
      },
      "mae_divergence": {
        "slope": 0.12438619687350112,
        "final_over_first": 2.556301365201096,
        "monotonic_frac": 1.0
      },
      "train_meta": {
        "n_params": 21648,
        "best_val_mae": 1.968866038890112,
        "best_epoch": 50,
        "epochs_run": 50,
        "train_time_sec": 778.8,
        "peak_vram_gb": 1.63
      }
    },
    "hybrid": {
      "at_horizons": {
        "horizons": [
          3,
          6,
          12
        ],
        "mae": {
          "h3": 1.431182991663307,
          "h6": 1.853417254127481,
          "h12": 2.368431176934879
        },
        "rmse": {
          "h3": 2.948083805686673,
          "h6": 4.030378342366178,
          "h12": 5.216789864867165
        },
        "mape": {
          "h3": 3.0912696944506806,
          "h6": 4.3007349813120515,
          "h12": 5.851797647297904
        }
      },
      "per_step": {
        "per_step": {
          "mae": [
            0.9478188036907925,
            1.2214727661894529,
            1.431182991663307,
            1.597024292045124,
            1.7337595331090678,
            1.853417254127481,
            1.9550077197724494,
            2.054172858961675,
            2.1403873321294817,
            2.2205709600192103,
            2.2930603492536137,
            2.368431176934879
          ],
          "rmse": [
            1.7140028616510443,
            2.3883024681689404,
            2.948083805686673,
            3.389069909924458,
            3.7355529299646184,
            4.030378342366178,
            4.271172288880217,
            4.49999984377367,
            4.7066348127243,
            4.882340707383458,
            5.053757022201719,
            5.216789864867165
          ],
          "mape": [
            1.9624299642182794,
            2.561293885471436,
            3.0912696944506806,
            3.5504873733062094,
            3.9504162200364346,
            4.3007349813120515,
            4.610310593556988,
            4.906379756327554,
            5.179058502391136,
            5.387740136751152,
            5.653043705749193,
            5.851797647297904
          ]
        },
        "mean": {
          "mae": 1.8180255031580448,
          "rmse": 3.9030070714660368,
          "mape": 4.250413538405751
        }
      },
      "mae_divergence": {
        "slope": 0.12089645376006394,
        "final_over_first": 2.498822736700562,
        "monotonic_frac": 1.0
      },
      "train_meta": {
        "n_params": 25744,
        "best_val_mae": 1.9680752612295604,
        "best_epoch": 43,
        "epochs_run": 50,
        "train_time_sec": 799.5,
        "peak_vram_gb": 1.63
      }
    },
    "identity": {
      "at_horizons": {
        "horizons": [
          3,
          6,
          12
        ],
        "mae": {
          "h3": 1.5047868523838244,
          "h6": 2.0547469489217134,
          "h12": 2.8614203591438305
        },
        "rmse": {
          "h3": 3.2669369972874387,
          "h6": 4.7731158410259535,
          "h12": 6.536375548513908
        },
        "mape": {
          "h3": 3.154999994573843,
          "h6": 4.5820974715773,
          "h12": 6.910482315726024
        }
      },
      "per_step": {
        "per_step": {
          "mae": [
            0.9371309164656146,
            1.2576606084040516,
            1.5047868523838244,
            1.7107812273571983,
            1.8904535177607091,
            2.0547469489217134,
            2.208202644714841,
            2.3522839209147666,
            2.487983142998344,
            2.6166079735429326,
            2.740085199221948,
            2.8614203591438305
          ],
          "rmse": [
            1.756604593617235,
            2.578407316200262,
            3.2669369972874387,
            3.8492159884764963,
            4.340271387473181,
            4.7731158410259535,
            5.151996086126237,
            5.493184904832998,
            5.792051835053741,
            6.068028104979992,
            6.31405152761348,
            6.536375548513908
          ],
          "mape": [
            1.8494114218391022,
            2.562409881517084,
            3.154999994573843,
            3.6738830521052956,
            4.141499390290732,
            4.5820974715773,
            4.990932236561867,
            5.393350473275,
            5.778912518542621,
            6.163326108545737,
            6.531572964317091,
            6.910482315726024
          ]
        },
        "mean": {
          "mae": 2.051845275985815,
          "rmse": 4.660020010933411,
          "mape": 4.6444064857393075
        }
      },
      "mae_divergence": {
        "slope": 0.1668416416727141,
        "final_over_first": 3.053383800350612,
        "monotonic_frac": 1.0
      },
      "train_meta": {
        "n_params": 15148,
        "best_val_mae": 2.3034788256599787,
        "best_epoch": 27,
        "epochs_run": 37,
        "train_time_sec": 572.9,
        "peak_vram_gb": 1.62
      }
    }
  },
  "baselines_test": {
    "copy_last": {
      "at_horizons": {
        "horizons": [
          3,
          6,
          12
        ],
        "mae": {
          "h3": 1.597618756259542,
          "h6": 2.1789394027452116,
          "h12": 3.0483040850675622
        },
        "rmse": {
          "h3": 3.433004185049776,
          "h6": 4.98502060217504,
          "h12": 7.0145248677013345
        },
        "mape": {
          "h3": 3.241473599942097,
          "h6": 4.65283627748273,
          "h12": 6.834822135183395
        }
      },
      "per_step": {
        "per_step": {
          "mae": [
            0.976387717992984,
            1.332866444395514,
            1.597618756259542,
            1.815505242446705,
            2.005183555650144,
            2.1789394027452116,
            2.3409769983829514,
            2.494438619020689,
            2.6400480149037207,
            2.77982192999347,
            2.9150329990033383,
            3.0483040850675622
          ],
          "rmse": [
            1.8584347759787985,
            2.7265829919885918,
            3.433004185049776,
            4.026319774829936,
            4.535631147334993,
            4.98502060217504,
            5.390343635181668,
            5.760335998912401,
            6.10192822123207,
            6.421850890495464,
            6.724657731635261,
            7.0145248677013345
          ],
          "mape": [
            1.8587187311035318,
            2.635594111725463,
            3.241473599942097,
            3.760401020126997,
            4.223372525976348,
            4.65283627748273,
            5.056736855592153,
            5.4410640269389186,
            5.807031394557032,
            6.159321814137337,
            6.499730192965897,
            6.834822135183395
          ]
        },
        "mean": {
          "mae": 2.1770936471551527,
          "rmse": 4.914886235209611,
          "mape": 4.680925223810991
        }
      },
      "mae_divergence": {
        "slope": 0.1785262863407788,
        "final_over_first": 3.1220221525661045,
        "monotonic_frac": 1.0
      }
    },
    "seasonal_historical_average": {
      "at_horizons": {
        "horizons": [
          3,
          6,
          12
        ],
        "mae": {
          "h3": 3.0285712832187444,
          "h6": 3.0272421369822387,
          "h12": 3.023863848050533
        },
        "rmse": {
          "h3": 5.847447271295761,
          "h6": 5.8458095851472125,
          "h12": 5.841060017181468
        },
        "mape": {
          "h3": 7.1302240739503535,
          "h6": 7.127169820122528,
          "h12": 7.120751692782841
        }
      },
      "per_step": {
        "per_step": {
          "mae": [
            3.029310397857219,
            3.028938876543216,
            3.0285712832187444,
            3.028169968932994,
            3.0277167687946154,
            3.0272421369822387,
            3.026742750999313,
            3.0261932347559224,
            3.0256128163754266,
            3.025013529255308,
            3.0244413491520654,
            3.023863848050533
          ],
          "rmse": [
            5.8482328785665105,
            5.847839982486705,
            5.847447271295761,
            5.846989169310974,
            5.846427555893726,
            5.8458095851472125,
            5.84513464445313,
            5.84438355143271,
            5.843565081141876,
            5.842700225546564,
            5.841881629137474,
            5.841060017181468
          ],
          "mape": [
            7.132187935898276,
            7.13117768930547,
            7.1302240739503535,
            7.12924868888008,
            7.12820166792055,
            7.127169820122528,
            7.12613075555306,
            7.1250040766552765,
            7.123870512655294,
            7.12273863383524,
            7.121728463438831,
            7.120751692782841
          ]
        },
        "mean": {
          "mae": 3.0268180800764664,
          "rmse": 5.845122632632841,
          "mape": 7.126536167583151
        }
      },
      "mae_divergence": {
        "slope": -0.000500523856730098,
        "final_over_first": 0.9982020496115094,
        "monotonic_frac": 0.0
      }
    }
  },
  "reference_only": {
    "note": "DCRNN/Graph WaveNet 논문 PEMS-BAY test MAE. 축소 설정과 달라 직접 비교 아님.",
    "DCRNN_paper_mae": {
      "h3": 1.38,
      "h6": 1.74,
      "h12": 2.07
    },
    "GraphWaveNet_paper_mae": {
      "h3": 1.3,
      "h6": 1.63,
      "h12": 1.95
    },
    "HA_paper_mae": {
      "h3": 2.88,
      "h6": 2.88,
      "h12": 2.88
    }
  }
}