{
  "synthetic_dummy": false,
  "task": "urban-traffic-forecasting",
  "phase": "Phase 2-B — STGNN 학습 + RQ1 절제",
  "note": "SOTA 재현 아님(원리 재현). 결측=0 masked MAE/RMSE/MAPE. 논문값은 reference_only.",
  "dataset": {
    "name": "METR-LA",
    "shape_T_N": [
      34272,
      207
    ],
    "sample_freq_min": 5,
    "source": "liyaguang/DCRNN (연구용 공개)"
  },
  "protocol": {
    "seq_len_in": 12,
    "horizon": 12,
    "horizons_steps": [
      3,
      6,
      12
    ],
    "horizons_minutes": {
      "h3": 15,
      "h6": 30,
      "h12": 60
    },
    "split_windows": {
      "train": 23974,
      "val": 3425,
      "test": 6850
    },
    "eval_split": "test",
    "features": [
      "zscore_speed",
      "time_of_day"
    ],
    "loss": "masked_mae(원 단위)",
    "adj_edge_density": 0.0402
  },
  "run": {
    "seed": 42,
    "git_commit": "9baa6e1d9248d284ec0e2bff54e6bd2774f01b1c",
    "timestamp_utc": "20260704T064753Z",
    "epochs_cap": 50,
    "batch_size": 256,
    "lr": 0.001,
    "weight_decay": 0.0001,
    "early_stop_patience": 10,
    "hardware": {
      "platform": "Windows-11-10.0.26200-SP0",
      "device": "cuda",
      "gpu": "NVIDIA GeForce RTX 3060",
      "cuda_fallback_to_cpu": false
    }
  },
  "stgnn_test": {
    "fixed": {
      "at_horizons": {
        "horizons": [
          3,
          6,
          12
        ],
        "mae": {
          "h3": 3.111912913752467,
          "h6": 3.795131659311575,
          "h12": 4.888522863491897
        },
        "rmse": {
          "h3": 5.992683105619706,
          "h6": 7.526641504581645,
          "h12": 9.499657298403207
        },
        "mape": {
          "h3": 8.190078235454973,
          "h6": 10.520069390726663,
          "h12": 14.37972922379036
        }
      },
      "per_step": {
        "per_step": {
          "mae": [
            2.467675201517734,
            2.8325908939555164,
            3.111912913752467,
            3.358010409878748,
            3.58188074543668,
            3.795131659311575,
            4.000243534541505,
            4.187513914492462,
            4.370839039640402,
            4.545751999176362,
            4.71989952140978,
            4.888522863491897
          ],
          "rmse": [
            4.260648798713928,
            5.266275125538234,
            5.992683105619706,
            6.573554430001446,
            7.080744892558264,
            7.526641504581645,
            7.932444680566568,
            8.301117755966994,
            8.63549363942784,
            8.953328373703654,
            9.232142393928545,
            9.499657298403207
          ],
          "mape": [
            6.082318026706768,
            7.251052899621134,
            8.190078235454973,
            9.021166220556113,
            9.77365032821691,
            10.520069390726663,
            11.209632586088176,
            11.898384525157429,
            12.531917895341547,
            13.11150180991348,
            13.743763335892645,
            14.37972922379036
          ]
        },
        "mean": {
          "mae": 3.8216643913837607,
          "rmse": 7.437894333250835,
          "mape": 10.64277203978885
        }
      },
      "mae_divergence": {
        "slope": 0.21237108411880073,
        "final_over_first": 1.981023621133458,
        "monotonic_frac": 1.0
      },
      "train_meta": {
        "n_params": 15148,
        "best_val_mae": 3.4678767834390913,
        "best_epoch": 50,
        "epochs_run": 50,
        "train_time_sec": 319.6,
        "peak_vram_gb": 1.38
      }
    },
    "learned": {
      "at_horizons": {
        "horizons": [
          3,
          6,
          12
        ],
        "mae": {
          "h3": 2.998205007749736,
          "h6": 3.4971799795100895,
          "h12": 4.272683544278275
        },
        "rmse": {
          "h3": 5.690848205906478,
          "h6": 6.814707666637512,
          "h12": 8.290265499308763
        },
        "mape": {
          "h3": 8.055240099563765,
          "h6": 9.979422650390255,
          "h12": 13.070027173541066
        }
      },
      "per_step": {
        "per_step": {
          "mae": [
            2.491602313009416,
            2.783186681470597,
            2.998205007749736,
            3.1814370406513066,
            3.3433833695237833,
            3.4971799795100895,
            3.6406471257597457,
            3.7739841587782457,
            3.9036787916362257,
            4.026356315727799,
            4.14913731376469,
            4.272683544278275
          ],
          "rmse": [
            4.300413714675482,
            5.143149356240486,
            5.690848205906478,
            6.120382370007306,
            6.5013825734444515,
            6.814707666637512,
            7.11089380222643,
            7.39123470014959,
            7.632857892683358,
            7.870763724561847,
            8.08492965545512,
            8.290265499308763
          ],
          "mape": [
            6.310795205587769,
            7.257765158804438,
            8.055240099563765,
            8.743805825766193,
            9.367654159616183,
            9.979422650390255,
            10.533611253027013,
            11.104491798399655,
            11.687250772745431,
            12.112383919720807,
            12.670509246845068,
            13.070027173541066
          ]
        },
        "mean": {
          "mae": 3.505123470154992,
          "rmse": 6.745985763441401,
          "mape": 10.07441310533397
        }
      },
      "mae_divergence": {
        "slope": 0.15429715615170764,
        "final_over_first": 1.714833672279597,
        "monotonic_frac": 1.0
      },
      "train_meta": {
        "n_params": 19288,
        "best_val_mae": 3.2184423293386186,
        "best_epoch": 49,
        "epochs_run": 50,
        "train_time_sec": 321.4,
        "peak_vram_gb": 1.0
      }
    },
    "hybrid": {
      "at_horizons": {
        "horizons": [
          3,
          6,
          12
        ],
        "mae": {
          "h3": 2.9977587338043796,
          "h6": 3.515751346780449,
          "h12": 4.298477434995212
        },
        "rmse": {
          "h3": 5.66153054170842,
          "h6": 6.8416204937667855,
          "h12": 8.318229872857831
        },
        "mape": {
          "h3": 8.025295281713758,
          "h6": 9.946934357595481,
          "h12": 13.027034683941958
        }
      },
      "per_step": {
        "per_step": {
          "mae": [
            2.4661266313254266,
            2.7695494988479035,
            2.9977587338043796,
            3.187788382499909,
            3.359125367147627,
            3.515751346780449,
            3.6636484431505174,
            3.800016880646586,
            3.928049409814922,
            4.053325021250073,
            4.176675192651017,
            4.298477434995212
          ],
          "rmse": [
            4.2234521902592626,
            5.085929532987047,
            5.66153054170842,
            6.119337999786799,
            6.510406677233606,
            6.8416204937667855,
            7.149131098490973,
            7.416660160320658,
            7.657071402900792,
            7.894982919274995,
            8.114386173417662,
            8.318229872857831
          ],
          "mape": [
            6.221809758116207,
            7.182637920700497,
            8.025295281713758,
            8.723639224099122,
            9.292431988275956,
            9.946934357595481,
            10.467681602249392,
            11.043282472911011,
            11.559588037829906,
            12.086445769466843,
            12.549534848017437,
            13.027034683941958
          ]
        },
        "mean": {
          "mae": 3.518024361909502,
          "rmse": 6.749394921917069,
          "mape": 10.010526328743133
        }
      },
      "mae_divergence": {
        "slope": 0.15867423381173962,
        "final_over_first": 1.7430075894703687,
        "monotonic_frac": 1.0
      },
      "train_meta": {
        "n_params": 23384,
        "best_val_mae": 3.217612155846187,
        "best_epoch": 50,
        "epochs_run": 50,
        "train_time_sec": 336.2,
        "peak_vram_gb": 1.0
      }
    },
    "identity": {
      "at_horizons": {
        "horizons": [
          3,
          6,
          12
        ],
        "mae": {
          "h3": 3.1465458488622047,
          "h6": 3.8412254809972732,
          "h12": 4.950830479758504
        },
        "rmse": {
          "h3": 6.168978506978054,
          "h6": 7.716810509557184,
          "h12": 9.707827229468233
        },
        "mape": {
          "h3": 8.335479259619701,
          "h6": 10.7536829599764,
          "h12": 14.724330271370423
        }
      },
      "per_step": {
        "per_step": {
          "mae": [
            2.501221084363392,
            2.8658216826348775,
            3.1465458488622047,
            3.394487965971696,
            3.6229384625127907,
            3.8412254809972732,
            4.048043273943488,
            4.238351818257026,
            4.423522665847745,
            4.602210645220926,
            4.779018540181988,
            4.950830479758504
          ],
          "rmse": [
            4.396695507607148,
            5.4316344149580225,
            6.168978506978054,
            6.759027271072128,
            7.263707455401099,
            7.716810509557184,
            8.120871163763816,
            8.497108893009658,
            8.829156325197413,
            9.14559535207514,
            9.424248825043975,
            9.707827229468233
          ],
          "mape": [
            6.168568955377278,
            7.379149757308621,
            8.335479259619701,
            9.220983224263755,
            10.002156340762111,
            10.7536829599764,
            11.473221315749916,
            12.174196512452728,
            12.811680694506542,
            13.47317026208919,
            14.120051651245477,
            14.724330271370423
          ]
        },
        "mean": {
          "mae": 3.8678514957126597,
          "rmse": 7.621805121177657,
          "mape": 10.886389267060176
        }
      },
      "mae_divergence": {
        "slope": 0.2152180419627288,
        "final_over_first": 1.979365403046162,
        "monotonic_frac": 1.0
      },
      "train_meta": {
        "n_params": 15148,
        "best_val_mae": 3.4998238512447903,
        "best_epoch": 50,
        "epochs_run": 50,
        "train_time_sec": 321.4,
        "peak_vram_gb": 1.0
      }
    }
  },
  "baselines_test": {
    "copy_last": {
      "at_horizons": {
        "horizons": [
          3,
          6,
          12
        ],
        "mae": {
          "h3": 4.016948702606489,
          "h6": 5.093775265444338,
          "h12": 6.795155269878107
        },
        "rmse": {
          "h3": 8.693764095631835,
          "h6": 11.13221247802156,
          "h12": 14.208575527232643
        },
        "mape": {
          "h3": 9.394963543562318,
          "h6": 12.213261008244695,
          "h12": 16.713969356118223
        }
      },
      "per_step": {
        "per_step": {
          "mae": [
            3.048439815045685,
            3.598947191343487,
            4.016948702606489,
            4.3912941064598625,
            4.746795956177562,
            5.093775265444338,
            5.41493851191196,
            5.72298675443147,
            6.018049203974263,
            6.286376561495383,
            6.542157311928271,
            6.795155269878107
          ],
          "rmse": [
            6.075700245741871,
            7.621392329725776,
            8.693764095631835,
            9.59191768600669,
            10.398131929846008,
            11.13221247802156,
            11.768584529038314,
            12.358896290711018,
            12.909452277602105,
            13.371696079694763,
            13.798311221625543,
            14.208575527232643
          ],
          "mape": [
            6.841818856077851,
            8.29057647741453,
            9.394963543562318,
            10.381865093514394,
            11.312414792765711,
            12.213261008244695,
            13.047194935463347,
            13.862254649763479,
            14.623413638703031,
            15.33681266860086,
            16.020506795221916,
            16.713969356118223
          ]
        },
        "mean": {
          "mae": 5.139655387558073,
          "rmse": 10.99405289090651,
          "mape": 12.336587651287529
        }
      },
      "mae_divergence": {
        "slope": 0.332070864438613,
        "final_over_first": 2.2290600051673555,
        "monotonic_frac": 1.0
      }
    },
    "seasonal_historical_average": {
      "at_horizons": {
        "horizons": [
          3,
          6,
          12
        ],
        "mae": {
          "h3": 4.186671045417986,
          "h6": 4.186699090256109,
          "h12": 4.186862040942669
        },
        "rmse": {
          "h3": 7.852025951942078,
          "h6": 7.852103979707439,
          "h12": 7.852273560723628
        },
        "mape": {
          "h3": 13.033502073279285,
          "h6": 13.033539108129922,
          "h12": 13.033811770971838
        }
      },
      "per_step": {
        "per_step": {
          "mae": [
            4.186907771149811,
            4.186786276241645,
            4.186671045417986,
            4.186649702807271,
            4.1865492512799545,
            4.186699090256109,
            4.186706367805327,
            4.186742911383147,
            4.18679681234647,
            4.186767447594376,
            4.18683931591624,
            4.186862040942669
          ],
          "rmse": [
            7.852068550566064,
            7.852048885430833,
            7.852025951942078,
            7.852027760406796,
            7.851998969230681,
            7.852103979707439,
            7.852130420439501,
            7.8521569305984915,
            7.852180652396207,
            7.85219669961716,
            7.852247543785254,
            7.852273560723628
          ],
          "mape": [
            13.0339512999849,
            13.033724140114867,
            13.033502073279285,
            13.033437827245425,
            13.033247674637739,
            13.033539108129922,
            13.033545176800468,
            13.033617627487684,
            13.033698800524457,
            13.033650480013184,
            13.033766232197703,
            13.033811770971838
          ]
        },
        "mean": {
          "mae": 4.186748169428418,
          "rmse": 7.852121658737011,
          "mape": 13.033624350948955
        }
      },
      "mae_divergence": {
        "slope": 6.89841112697212e-06,
        "final_over_first": 0.9999890778088171,
        "monotonic_frac": 0.5454545454545454
      }
    }
  },
  "reference_only": {
    "note": "DCRNN 논문(Li+ 2018 Table 1) METR-LA test. 우리 소형/축소 설정과 달라 직접 비교 아님.",
    "DCRNN_paper_mae": {
      "h3": 2.77,
      "h6": 3.15,
      "h12": 3.6
    },
    "GraphWaveNet_paper_mae": {
      "h3": 2.69,
      "h6": 3.07,
      "h12": 3.53
    },
    "HA_paper_mae": {
      "h3": 4.16,
      "h6": 4.16,
      "h12": 4.16
    }
  }
}