{
  "synthetic_dummy": false,
  "task": "task-02-traffic-stgnn",
  "phase": "Phase 2-B — STGNN 학습 + RQ1 절제",
  "note": "SOTA 재현 아님(원리 재현). 결측=0 masked MAE/RMSE/MAPE. 논문값은 reference_only.",
  "dataset": {
    "name": "METR-LA",
    "shape_T_N": [
      34272,
      207
    ],
    "sample_freq_min": 5,
    "source": "liyaguang/DCRNN (연구용 공개)"
  },
  "protocol": {
    "seq_len_in": 12,
    "horizon": 12,
    "horizons_steps": [
      3,
      6,
      12
    ],
    "horizons_minutes": {
      "h3": 15,
      "h6": 30,
      "h12": 60
    },
    "split_windows": {
      "train": 23974,
      "val": 3425,
      "test": 6850
    },
    "eval_split": "test",
    "features": [
      "zscore_speed",
      "time_of_day"
    ],
    "loss": "masked_mae(원 단위)",
    "adj_edge_density": 0.0402
  },
  "run": {
    "seed": 42,
    "git_commit": "ed0d168a5bda7f00564766a4db8071e1c8c9e8ce",
    "timestamp_utc": "20260704T053515Z",
    "epochs_cap": 50,
    "batch_size": 256,
    "lr": 0.001,
    "weight_decay": 0.0001,
    "early_stop_patience": 10,
    "hardware": {
      "platform": "Windows-11-10.0.26200-SP0",
      "device": "cuda",
      "gpu": "NVIDIA GeForce RTX 3060",
      "cuda_fallback_to_cpu": false
    }
  },
  "stgnn_test": {
    "fixed": {
      "at_horizons": {
        "horizons": [
          3,
          6,
          12
        ],
        "mae": {
          "h3": 3.111927162622701,
          "h6": 3.7951662046408403,
          "h12": 4.8885562316947215
        },
        "rmse": {
          "h3": 5.992531680404147,
          "h6": 7.526513970193157,
          "h12": 9.499648586424346
        },
        "mape": {
          "h3": 8.190114923527402,
          "h6": 10.520172412072473,
          "h12": 14.379481119670224
        }
      },
      "per_step": {
        "per_step": {
          "mae": [
            2.46772378686548,
            2.8326069423583276,
            3.111927162622701,
            3.35805689976691,
            3.581894562398471,
            3.7951662046408403,
            4.0002969267983755,
            4.187535476487129,
            4.3708760442363594,
            4.545775367145603,
            4.719909428418512,
            4.8885562316947215
          ],
          "rmse": [
            4.26055808750214,
            5.266206997135333,
            5.992531680404147,
            6.573344934484145,
            7.080651673156495,
            7.526513970193157,
            7.932318737513709,
            8.300990792941244,
            8.635367776584701,
            8.953127856550703,
            9.23206288664754,
            9.499648586424346
          ],
          "mape": [
            6.0826843067802745,
            7.251080100448096,
            8.190114923527402,
            9.02129367170458,
            9.773734187019164,
            10.520172412072473,
            11.209971335165482,
            11.898501110364663,
            12.53181617614397,
            13.11142277569393,
            13.74374806574306,
            14.379481119670224
          ]
        },
        "mean": {
          "mae": 3.821693752786119,
          "rmse": 7.4377769982948045,
          "mape": 10.642835015361108
        }
      },
      "mae_divergence": {
        "slope": 0.21237051009123897,
        "final_over_first": 1.9809981399515542,
        "monotonic_frac": 1.0
      },
      "train_meta": {
        "n_params": 15148,
        "best_val_mae": 3.4679179191589355,
        "best_epoch": 50,
        "epochs_run": 50,
        "train_time_sec": 319.5,
        "peak_vram_gb": 1.38
      }
    },
    "learned": {
      "at_horizons": {
        "horizons": [
          3,
          6,
          12
        ],
        "mae": {
          "h3": 2.9983579562722005,
          "h6": 3.498658157998604,
          "h12": 4.275855435259541
        },
        "rmse": {
          "h3": 5.688246379298107,
          "h6": 6.818567794869524,
          "h12": 8.295765945999209
        },
        "mape": {
          "h3": 8.065939520818038,
          "h6": 9.990897069579402,
          "h12": 13.087755125768064
        }
      },
      "per_step": {
        "per_step": {
          "mae": [
            2.489954970136931,
            2.782218276942923,
            2.9983579562722005,
            3.1821732420270896,
            3.3446979042296894,
            3.498658157998604,
            3.6423403421842786,
            3.7765369736431906,
            3.9067000813901305,
            4.028829806422577,
            4.152861869375456,
            4.275855435259541
          ],
          "rmse": [
            4.295117987048631,
            5.140136812664907,
            5.688246379298107,
            6.122248934124083,
            6.503922450709827,
            6.818567794869524,
            7.1153099260857084,
            7.395418866176695,
            7.638776017799672,
            7.874524901889537,
            8.089560668038427,
            8.295765945999209
          ],
          "mape": [
            6.305730649018912,
            7.254575493377493,
            8.065939520818038,
            8.755395401647997,
            9.368812354973228,
            9.990897069579402,
            10.544295460051845,
            11.12236842341568,
            11.706073053841703,
            12.13771172885168,
            12.694602295049279,
            13.087755125768064
          ]
        },
        "mean": {
          "mae": 3.5065987513235513,
          "rmse": 6.748133057058695,
          "mape": 10.086179714699446
        }
      },
      "mae_divergence": {
        "slope": 0.15474067828159263,
        "final_over_first": 1.717242073267051,
        "monotonic_frac": 1.0
      },
      "train_meta": {
        "n_params": 19288,
        "best_val_mae": 3.219680121966771,
        "best_epoch": 49,
        "epochs_run": 50,
        "train_time_sec": 314.5,
        "peak_vram_gb": 1.0
      }
    },
    "hybrid": {
      "at_horizons": {
        "horizons": [
          3,
          6,
          12
        ],
        "mae": {
          "h3": 3.007262677790441,
          "h6": 3.5247236522488308,
          "h12": 4.30720425708277
        },
        "rmse": {
          "h3": 5.664968342007272,
          "h6": 6.849065522015889,
          "h12": 8.329271183163874
        },
        "mape": {
          "h3": 8.14535574966385,
          "h6": 10.079944000633757,
          "h12": 13.170599836835029
        }
      },
      "per_step": {
        "per_step": {
          "mae": [
            2.4753180078676924,
            2.77641762070754,
            3.007262677790441,
            3.197644832265879,
            3.363560528652611,
            3.5247236522488308,
            3.6705204268421516,
            3.808534076782808,
            3.9394942536042823,
            4.063626835222997,
            4.185295571131647,
            4.30720425708277
          ],
          "rmse": [
            4.232235858892909,
            5.085748665786903,
            5.664968342007272,
            6.126607686623648,
            6.51328540482248,
            6.849065522015889,
            7.153469168781015,
            7.425775402450496,
            7.667734641106886,
            7.904298388154742,
            8.121164034598978,
            8.329271183163874
          ],
          "mape": [
            6.2782180343924185,
            7.269170532874328,
            8.14535574966385,
            8.821739694675513,
            9.392842678223436,
            10.079944000633757,
            10.586298475331741,
            11.151924345576296,
            11.700694618021906,
            12.20169550387399,
            12.694180660129142,
            13.170599836835029
          ]
        },
        "mean": {
          "mae": 3.5266335616833047,
          "rmse": 6.756135358200424,
          "mape": 10.124388677519283
        }
      },
      "mae_divergence": {
        "slope": 0.15879427945065258,
        "final_over_first": 1.740060971314597,
        "monotonic_frac": 1.0
      },
      "train_meta": {
        "n_params": 23384,
        "best_val_mae": 3.2177132197788785,
        "best_epoch": 50,
        "epochs_run": 50,
        "train_time_sec": 328.4,
        "peak_vram_gb": 1.0
      }
    },
    "identity": {
      "at_horizons": {
        "horizons": [
          3,
          6,
          12
        ],
        "mae": {
          "h3": 3.1487072750366703,
          "h6": 3.84140278543765,
          "h12": 4.952673615723642
        },
        "rmse": {
          "h3": 6.169371288528497,
          "h6": 7.726000987127691,
          "h12": 9.706816732517833
        },
        "mape": {
          "h3": 8.237025681721873,
          "h6": 10.644246563150526,
          "h12": 14.68587953747997
        }
      },
      "per_step": {
        "per_step": {
          "mae": [
            2.5120875256239064,
            2.871960060101343,
            3.1487072750366703,
            3.3966878067740067,
            3.6236366089305183,
            3.84140278543765,
            4.045484968809699,
            4.238191993167626,
            4.422528023939709,
            4.60303028034027,
            4.779550889891181,
            4.952673615723642
          ],
          "rmse": [
            4.417621204176028,
            5.444222648652522,
            6.169371288528497,
            6.760882175930116,
            7.2717473853483465,
            7.726000987127691,
            8.14038232188636,
            8.508276612858559,
            8.84489543462195,
            9.146069410881536,
            9.430898490254693,
            9.706816732517833
          ],
          "mape": [
            6.103266327403233,
            7.283882140109123,
            8.237025681721873,
            9.103859289190035,
            9.884335777094542,
            10.644246563150526,
            11.369736651500896,
            12.07818906489836,
            12.743880808607116,
            13.41043993600839,
            14.053841472136346,
            14.68587953747997
          ]
        },
        "mean": {
          "mae": 3.8696618194813515,
          "rmse": 7.630598724398677,
          "mape": 10.799881937441699
        }
      },
      "mae_divergence": {
        "slope": 0.21458732488896057,
        "final_over_first": 1.9715370444720421,
        "monotonic_frac": 1.0
      },
      "train_meta": {
        "n_params": 15148,
        "best_val_mae": 3.4999431371688843,
        "best_epoch": 49,
        "epochs_run": 50,
        "train_time_sec": 299.8,
        "peak_vram_gb": 1.0
      }
    }
  },
  "baselines_test": {
    "copy_last": {
      "at_horizons": {
        "horizons": [
          3,
          6,
          12
        ],
        "mae": {
          "h3": 4.016948702606489,
          "h6": 5.093775265444338,
          "h12": 6.795155269878107
        },
        "rmse": {
          "h3": 8.693764095631835,
          "h6": 11.13221247802156,
          "h12": 14.208575527232643
        },
        "mape": {
          "h3": 9.394963543562318,
          "h6": 12.213261008244695,
          "h12": 16.713969356118223
        }
      },
      "per_step": {
        "per_step": {
          "mae": [
            3.048439815045685,
            3.598947191343487,
            4.016948702606489,
            4.3912941064598625,
            4.746795956177562,
            5.093775265444338,
            5.41493851191196,
            5.72298675443147,
            6.018049203974263,
            6.286376561495383,
            6.542157311928271,
            6.795155269878107
          ],
          "rmse": [
            6.075700245741871,
            7.621392329725776,
            8.693764095631835,
            9.59191768600669,
            10.398131929846008,
            11.13221247802156,
            11.768584529038314,
            12.358896290711018,
            12.909452277602105,
            13.371696079694763,
            13.798311221625543,
            14.208575527232643
          ],
          "mape": [
            6.841818856077851,
            8.29057647741453,
            9.394963543562318,
            10.381865093514394,
            11.312414792765711,
            12.213261008244695,
            13.047194935463347,
            13.862254649763479,
            14.623413638703031,
            15.33681266860086,
            16.020506795221916,
            16.713969356118223
          ]
        },
        "mean": {
          "mae": 5.139655387558073,
          "rmse": 10.99405289090651,
          "mape": 12.336587651287529
        }
      },
      "mae_divergence": {
        "slope": 0.332070864438613,
        "final_over_first": 2.2290600051673555,
        "monotonic_frac": 1.0
      }
    },
    "seasonal_historical_average": {
      "at_horizons": {
        "horizons": [
          3,
          6,
          12
        ],
        "mae": {
          "h3": 4.186671045417986,
          "h6": 4.186699090256109,
          "h12": 4.186862040942669
        },
        "rmse": {
          "h3": 7.852025951942078,
          "h6": 7.852103979707439,
          "h12": 7.852273560723628
        },
        "mape": {
          "h3": 13.033502073279285,
          "h6": 13.033539108129922,
          "h12": 13.033811770971838
        }
      },
      "per_step": {
        "per_step": {
          "mae": [
            4.186907771149811,
            4.186786276241645,
            4.186671045417986,
            4.186649702807271,
            4.1865492512799545,
            4.186699090256109,
            4.186706367805327,
            4.186742911383147,
            4.18679681234647,
            4.186767447594376,
            4.18683931591624,
            4.186862040942669
          ],
          "rmse": [
            7.852068550566064,
            7.852048885430833,
            7.852025951942078,
            7.852027760406796,
            7.851998969230681,
            7.852103979707439,
            7.852130420439501,
            7.8521569305984915,
            7.852180652396207,
            7.85219669961716,
            7.852247543785254,
            7.852273560723628
          ],
          "mape": [
            13.0339512999849,
            13.033724140114867,
            13.033502073279285,
            13.033437827245425,
            13.033247674637739,
            13.033539108129922,
            13.033545176800468,
            13.033617627487684,
            13.033698800524457,
            13.033650480013184,
            13.033766232197703,
            13.033811770971838
          ]
        },
        "mean": {
          "mae": 4.186748169428418,
          "rmse": 7.852121658737011,
          "mape": 13.033624350948955
        }
      },
      "mae_divergence": {
        "slope": 6.89841112697212e-06,
        "final_over_first": 0.9999890778088171,
        "monotonic_frac": 0.5454545454545454
      }
    }
  },
  "reference_only": {
    "note": "DCRNN 논문(Li+ 2018 Table 1) METR-LA test. 우리 소형/축소 설정과 달라 직접 비교 아님.",
    "DCRNN_paper_mae": {
      "h3": 2.77,
      "h6": 3.15,
      "h12": 3.6
    },
    "GraphWaveNet_paper_mae": {
      "h3": 2.69,
      "h6": 3.07,
      "h12": 3.53
    },
    "HA_paper_mae": {
      "h3": 4.16,
      "h6": 4.16,
      "h12": 4.16
    }
  }
}